langchain_seekrflow/__init__.py
langchain_seekrflow/seekrflow.py
langchain_seekrflow-0.1.0.dist-info/LICENSE
langchain_seekrflow-0.1.0.dist-info/METADATA
langchain_seekrflow-0.1.0.dist-info/WHEEL
langchain_seekrflow-0.1.0.dist-info/RECORD
