Metadata-Version: 2.3
Name: langchain-seekrflow
Version: 0.1.0
Summary: LangChain integration for SeekrFlow chat models
License: MIT
Author: Ben Faircloth
Author-email: bfaircloth@seekr.com
Requires-Python: >=3.10,<4.0
Classifier: License :: OSI Approved :: MIT License
Classifier: Programming Language :: Python :: 3
Classifier: Programming Language :: Python :: 3.10
Classifier: Programming Language :: Python :: 3.11
Classifier: Programming Language :: Python :: 3.12
Classifier: Programming Language :: Python :: 3.13
Requires-Dist: langchain (>=0.3.21,<0.4.0)
Requires-Dist: seekrai (>=0.4.4,<0.5.0)
